postgresql/__init__.py
postgresql/dbmanager.py
postgresql/ephemeralpostgresqldbcontext.py
postgresql/ephemeralpostgresqldbcontextbuilder.py
postgresql/filesmanager.py
ephemerals_postgresql-1.0.0.dist-info/LICENSE.md
ephemerals_postgresql-1.0.0.dist-info/METADATA
ephemerals_postgresql-1.0.0.dist-info/WHEEL
ephemerals_postgresql-1.0.0.dist-info/top_level.txt
ephemerals_postgresql-1.0.0.dist-info/RECORD
